auto_stomp/__init__.py
auto_stomp/frame.py
auto_stomp/stomp.py
auto_stomp-0.0.2.dist-info/METADATA
auto_stomp-0.0.2.dist-info/WHEEL
auto_stomp-0.0.2.dist-info/top_level.txt
auto_stomp-0.0.2.dist-info/RECORD
