Metadata-Version: 2.1
Name: auto-stomp
Version: 0.0.2
Summary: A simple STOMP client for WebSocket with asyncio support
Home-page: https://github.com/sieunie/auto-stomp
Author: sieun lee
Author-email: leesieun08@naver.com
License: UNKNOWN
Platform: UNKNOWN
Classifier: Programming Language :: Python :: 3
Classifier: License :: OSI Approved :: MIT License
Classifier: Operating System :: OS Independent
Requires-Python: >=3.7
Requires-Dist: websockets>=10.0
